arcus_data/__init__.py
arcus_data/api.py
arcus_data-0.0.1.dist-info/LICENSE
arcus_data-0.0.1.dist-info/METADATA
arcus_data-0.0.1.dist-info/WHEEL
arcus_data-0.0.1.dist-info/top_level.txt
arcus_data-0.0.1.dist-info/RECORD
